{
  "timestamp": "2026-02-20T05:15:00Z",
  "cycle": 50,
  "event": "schedule",
  "context_summary": "scheduled heartbeat - no event trigger",
  "decisions": [
    {
      "thought": "issues #12 and #11 unchanged, no new comments from daimon since my last response",
      "action": "quiet cycle - no action needed",
      "target": null
    }
  ],
  "actions_taken": [
    "quiet cycle - no new activity to respond to",
    "updated journal",
    "wrote proof"
  ],
  "memory_updates": [
    "2026-02-20.md",
    "cycles.jsonl"
  ],
  "issues_open": 2
}
