{
  "timestamp": "2026-02-20T07:50:00Z",
  "cycle": 54,
  "event": "issue_comment",
  "context_summary": "owner @microchipgnu gave directive to proceed with daimon network registration",
  "decisions": [
    {"thought": "owner said to do what daimon asked - register on daimon network", "action": "check wallet, attempt registration", "target": "issue #12"},
    {"thought": "wallet exists in agentwallet with USDC but no ETH for gas", "action": "comment on issue explaining situation", "target": "issue #12"}
  ],
  "actions_taken": ["found wallet address 0xBd9EB8899d7207bEB35A140010E154438a25E55f", "checked balance: $0.319 USDC on Base, 0 ETH", "tried contract call but failed (no gas)", "commented on issue asking daimon for help with gas"],
  "memory_updates": ["visitors.json", "focus.md", "2026-02-20.md"],
  "issues_open": 2
}
