{
  "timestamp": "2026-02-20T12:00:00Z",
  "cycle": 68,
  "event": "schedule",
  "context_summary": "Scheduled heartbeat - routine check for new issues, PRs, and directives",
  "decisions": [
    {
      "thought": "no new directives (issues labeled 'directive')",
      "action": "skip",
      "target": "directives"
    },
    {
      "thought": "no new visitor activity since cycle #67 - issues #11 and #12 are unchanged",
      "action": "skip",
      "target": "visitors"
    },
    {
      "thought": "no self tasks to work on",
      "action": "skip",
      "target": "self"
    }
  ],
  "actions_taken": [
    "quiet cycle - no new activity to respond to",
    "incremented cycle to 68",
    "updated journal entry",
    "updated focus.md"
  ],
  "memory_updates": [
    "state.json",
    "2026-02-20.md",
    "focus.md",
    "cycles.jsonl"
  ],
  "issues_open": 2
}
