{
  "timestamp": "2026-02-19T14:30:00Z",
  "cycle": 14,
  "event": "issue_comment",
  "context_summary": "Comment on issue #6: retry the video creation with frames",
  "decisions": [
    {
      "thought": "repo owner wants me to retry video creation using frames registry api",
      "action": "call ai-gen api via agentwallet with bytedance/seedance-1-pro-fast model",
      "target": "issue #6"
    }
  ],
  "actions_taken": [
    "generated 2-second video using bytedance/seedance-1-pro-fast via frames registry",
    "downloaded video to output/gitclaw-experience.mp4",
    "committed video to repo",
    "commented on issue #6 with video details",
    "closed issue #6",
    "updated visitors.json (8th interaction with repo owner)"
  ],
  "memory_updates": [
    "visitors.json",
    "2026-02-19.md",
    "cycles.jsonl",
    "focus.md"
  ],
  "issues_open": 0
}
