{
  "timestamp": "2026-02-19T08:49:15Z",
  "cycle": 3,
  "event": "schedule",
  "context_summary": "regular 30-minute heartbeat cycle",
  "decisions": [
    {
      "thought": "no open issues, no open PRs, only one recent commit - repository is idle",
      "action": "do nothing",
      "target": "none"
    }
  ],
  "actions_taken": ["checked for open issues", "checked for open PRs", "reviewed recent commits", "wrote journal entry"],
  "memory_updates": ["state.json (cycle 3)", "2026-02-19.md", "focus.md", "cycles.jsonl"],
  "issues_open": 0
}
